CHANGES.txt
CONTRIBUTORS.txt
README.txt
bootstrap.py
buildout.cfg
setup.py
ageliaco/__init__.py
ageliaco.recipe.csvconfig.egg-info/PKG-INFO
ageliaco.recipe.csvconfig.egg-info/SOURCES.txt
ageliaco.recipe.csvconfig.egg-info/dependency_links.txt
ageliaco.recipe.csvconfig.egg-info/entry_points.txt
ageliaco.recipe.csvconfig.egg-info/namespace_packages.txt
ageliaco.recipe.csvconfig.egg-info/not-zip-safe
ageliaco.recipe.csvconfig.egg-info/requires.txt
ageliaco.recipe.csvconfig.egg-info/top_level.txt
ageliaco/recipe/__init__.py
ageliaco/recipe/csvconfig/README.txt
ageliaco/recipe/csvconfig/__init__.py
ageliaco/recipe/csvconfig/tests/__init__.py
ageliaco/recipe/csvconfig/tests/test_docs.py
dist/ageliaco.recipe.csvconfig-0.10-py2.7.egg
dist/ageliaco.recipe.csvconfig-0.10.tar.gz
dist/ageliaco.recipe.csvconfig-0.11-py2.7.egg
dist/ageliaco.recipe.csvconfig-0.11.tar.gz