Metadata-Version: 1.1
Name: ageliaco.recipe.csvconfig
Version: 0.12
Summary: Use a CSV file to populate buildout templates
Home-page: https://github.com/renfers/ageliaco.recipe.csvconfig
Author: Serge Renfer
Author-email: serge.renfer@gmail.com
License: ZPL
Keywords: buildout recipe
Platform: UNKNOWN
Classifier: Framework :: Buildout
Classifier: Intended Audience :: Developers
Classifier: Topic :: Software Development :: Build Tools
Classifier: License :: OSI Approved :: Zope Public License
